kaparoo/__about__.py
kaparoo/__init__.py
kaparoo/py.typed
kaparoo/data/__init__.py
kaparoo/data/utils.py
kaparoo/data/files/__init__.py
kaparoo/data/files/base.py
kaparoo/filesystem/__init__.py
kaparoo/filesystem/directory.py
kaparoo/filesystem/exceptions.py
kaparoo/filesystem/existence.py
kaparoo/filesystem/types.py
kaparoo/filesystem/utils.py
kaparoo/utils/__init__.py
kaparoo/utils/optional.py
kaparoo/utils/types.py
kaparoo_python-0.1.12.dist-info/METADATA
kaparoo_python-0.1.12.dist-info/WHEEL
kaparoo_python-0.1.12.dist-info/licenses/LICENSE
kaparoo_python-0.1.12.dist-info/RECORD
