Metadata-Version: 2.1
Name: kaparoo-python
Version: 0.1.12
Summary: Personally common and useful Python features
Project-URL: GitHub, https://www.github.com/kaparoo/kaparoo-python
Author-email: Jaewoo Park <kaparoo2001@gmail.com>
License: MIT License
License-File: LICENSE
Classifier: Development Status :: 4 - Beta
Classifier: Intended Audience :: Developers
Classifier: License :: OSI Approved :: MIT License
Classifier: Operating System :: OS Independent
Classifier: Programming Language :: Python
Classifier: Programming Language :: Python :: 3
Classifier: Programming Language :: Python :: 3 :: Only
Classifier: Programming Language :: Python :: Implementation :: CPython
Classifier: Typing :: Typed
Requires-Python: >=3.11
Provides-Extra: dev
Requires-Dist: hatch>=1.9.3; extra == 'dev'
Requires-Dist: mypy>=1.8.0; extra == 'dev'
Requires-Dist: pytest-order>=1.2.0; extra == 'dev'
Requires-Dist: pytest>=8.0.2; extra == 'dev'
Requires-Dist: ruff>=0.2.2; extra == 'dev'
